sphinx_nefertiti/__init__.py
sphinx_nefertiti/breadcrumbs.html
sphinx_nefertiti/colorsets-dropdown.html
sphinx_nefertiti/colorsets.py
sphinx_nefertiti/docsver.py
sphinx_nefertiti/domainindex.html
sphinx_nefertiti/exceptions.py
sphinx_nefertiti/extensions.html
sphinx_nefertiti/fonts.py
sphinx_nefertiti/footer.html
sphinx_nefertiti/genindex-single.html
sphinx_nefertiti/genindex-split.html
sphinx_nefertiti/genindex.html
sphinx_nefertiti/globaltoc.html
sphinx_nefertiti/header-links.html
sphinx_nefertiti/l10n.py
sphinx_nefertiti/layout.html
sphinx_nefertiti/lightdark-dropdown.html
sphinx_nefertiti/links.py
sphinx_nefertiti/locale-dropdown.html
sphinx_nefertiti/modal.html
sphinx_nefertiti/page.html
sphinx_nefertiti/pager.html
sphinx_nefertiti/pygments.py
sphinx_nefertiti/search.html
sphinx_nefertiti/searchbox.html
sphinx_nefertiti/searchresults.html
sphinx_nefertiti/sitemap.html
sphinx_nefertiti/theme.conf
sphinx_nefertiti/version-dropdown.html
sphinx_nefertiti/bin/nftt.py
sphinx_nefertiti/colorsets/colorsets.js
sphinx_nefertiti/colorsets/sphinx-nefertiti-blue.min.css
sphinx_nefertiti/colorsets/sphinx-nefertiti-blue.min.css.map
sphinx_nefertiti/colorsets/sphinx-nefertiti-default.min.css
sphinx_nefertiti/colorsets/sphinx-nefertiti-default.min.css.map
sphinx_nefertiti/colorsets/sphinx-nefertiti-green.min.css
sphinx_nefertiti/colorsets/sphinx-nefertiti-green.min.css.map
sphinx_nefertiti/colorsets/sphinx-nefertiti-indigo.min.css
sphinx_nefertiti/colorsets/sphinx-nefertiti-indigo.min.css.map
sphinx_nefertiti/colorsets/sphinx-nefertiti-orange.min.css
sphinx_nefertiti/colorsets/sphinx-nefertiti-orange.min.css.map
sphinx_nefertiti/colorsets/sphinx-nefertiti-pink.min.css
sphinx_nefertiti/colorsets/sphinx-nefertiti-pink.min.css.map
sphinx_nefertiti/colorsets/sphinx-nefertiti-purple.min.css
sphinx_nefertiti/colorsets/sphinx-nefertiti-purple.min.css.map
sphinx_nefertiti/colorsets/sphinx-nefertiti-red.min.css
sphinx_nefertiti/colorsets/sphinx-nefertiti-red.min.css.map
sphinx_nefertiti-0.9.2.dist-info/licenses/LICENSE.txt
sphinx_nefertiti-0.9.2.dist-info/METADATA
sphinx_nefertiti-0.9.2.dist-info/WHEEL
sphinx_nefertiti-0.9.2.dist-info/entry_points.txt
sphinx_nefertiti-0.9.2.dist-info/top_level.txt
sphinx_nefertiti-0.9.2.dist-info/RECORD
